fab_oidc2/__init__.py
fab_oidc2/security.py
fab_oidc2/store.py
fab_oidc2/views.py
fab_oidc2-0.0.3.dist-info/LICENCE.txt
fab_oidc2-0.0.3.dist-info/METADATA
fab_oidc2-0.0.3.dist-info/WHEEL
fab_oidc2-0.0.3.dist-info/top_level.txt
fab_oidc2-0.0.3.dist-info/RECORD
