Metadata-Version: 2.1
Name: fab-oidc2
Version: 0.0.3
Summary: Flask-AppBuilder SecurityManager for OpenIDConnect
Home-page: https://github.com/evinaypatil/fab-oidc2/
Author: evinaypatil
Author-email: evinaypatil@gmail.com
License: MIT
Project-URL: Bug Tracker, https://github.com/evinaypatil/fab-oidc2/issues
Project-URL: Documentation, https://github.com/evinaypatil/fab-oidc2/blob/main/README.md
Project-URL: Source Code, https://github.com/evinaypatil/fab-oidc2/
Platform: any
Classifier: Development Status :: 3 - Alpha
Classifier: Environment :: Web Environment
Classifier: Intended Audience :: Developers
Classifier: License :: OSI Approved :: MIT License
Classifier: Operating System :: OS Independent
Classifier: Programming Language :: Python
Classifier: Topic :: Software Development :: Libraries :: Python Modules
Classifier: Programming Language :: Python :: 3
Requires-Dist: Flask-AppBuilder (>=1.5.0)
Requires-Dist: flask-oidc2 (>=1.5.0)
Requires-Dist: Flask-Admin (>=1.4.1)
